users_microservice/__init__.py
users_microservice/admin.py
users_microservice/apps.py
users_microservice/authentication.py
users_microservice/dbrouter.py
users_microservice/models.py
users_microservice/tests.py
users_microservice/views.py
users_microservice-0.2.4.dist-info/METADATA
users_microservice-0.2.4.dist-info/WHEEL
users_microservice-0.2.4.dist-info/top_level.txt
users_microservice-0.2.4.dist-info/RECORD
