Metadata-Version: 2.1
Name: users-microservice
Version: 0.2.4
Summary: Django users Microservice
Home-page: https://github.com/QuantTrade-io/users-microservice
Author: QuantTrade.io
Author-email: dev@quanttrade.io
License: UNKNOWN
Platform: UNKNOWN
Classifier: Intended Audience :: Developers
Classifier: Operating System :: Unix
Classifier: Operating System :: MacOS
Classifier: Operating System :: Microsoft :: Windows
Classifier: Programming Language :: Python :: 3.9
Classifier: Programming Language :: Python :: 3.9
Classifier: Topic :: Software Development :: Libraries :: Python Modules
Requires-Dist: django
Requires-Dist: djangorestframework
Requires-Dist: requests
Provides-Extra: coverage
Requires-Dist: pytest-cov ; extra == 'coverage'
Provides-Extra: docs
Requires-Dist: sphinx ; extra == 'docs'
Provides-Extra: i18n
Requires-Dist: Babel ; extra == 'i18n'
Provides-Extra: pep8
Requires-Dist: flake8 ; extra == 'pep8'
Provides-Extra: release
Requires-Dist: zest.releaser ; extra == 'release'
Provides-Extra: test
Requires-Dist: pytest ; extra == 'test'
Requires-Dist: tox ; extra == 'test'
Requires-Dist: isort ; extra == 'test'
